FileToPics.py
README.rst
setup.py
FileToPics.egg-info/PKG-INFO
FileToPics.egg-info/SOURCES.txt
FileToPics.egg-info/dependency_links.txt
FileToPics.egg-info/top_level.txt
tests/__init__.py
tests/tests.py