Metadata-Version: 1.1
Name: FileToPics
Version: 0.0.6
Summary: This Python package can turn file(ppt/pptx/doc/docx/wps/pdf..) into pictures
Home-page: https://github.com/cmzhuzhu/FilesToPics
Author: Cao Mingzhu
Author-email: cmzhuzhu123@gmail.com
License: MIT
Keywords: Python file ppt doc images
Platform: UNKNOWN
Classifier: Development Status :: 5 - Production/Stable
Classifier: Intended Audience :: Developers
Classifier: License :: OSI Approved :: MIT License
Classifier: Programming Language :: Python :: 3.4
Classifier: Programming Language :: Python :: 3 :: Only
